README.txt
bootstrap.py
buildout.cfg
setup.py
src/gocept/__init__.py
src/gocept.httop.egg-info/PKG-INFO
src/gocept.httop.egg-info/SOURCES.txt
src/gocept.httop.egg-info/dependency_links.txt
src/gocept.httop.egg-info/entry_points.txt
src/gocept.httop.egg-info/namespace_packages.txt
src/gocept.httop.egg-info/not-zip-safe
src/gocept.httop.egg-info/requires.txt
src/gocept.httop.egg-info/top_level.txt
src/gocept/httop/__init__.py
src/gocept/httop/checker.py
src/gocept/httop/main.py