Metadata-Version: 1.0
Name: gocept.httop
Version: 1.0
Summary: An ncurses-based tool to monitor website responsiveness in real-time.
Home-page: UNKNOWN
Author: Christian Theune
Author-email: ct@gocept.com
License: ZPL 2.1
Platform: UNKNOWN
